llama_index/readers/rayyan/__init__.py
llama_index/readers/rayyan/base.py
llama_index_readers_rayyan-0.4.1.dist-info/METADATA
llama_index_readers_rayyan-0.4.1.dist-info/WHEEL
llama_index_readers_rayyan-0.4.1.dist-info/licenses/LICENSE
llama_index_readers_rayyan-0.4.1.dist-info/RECORD
