Metadata-Version: 2.4
Name: llama-index-readers-rayyan
Version: 0.4.1
Summary: llama-index readers rayyan integration
Author-email: Your Name <you@example.com>
Maintainer: hammady
License-Expression: MIT
License-File: LICENSE
Keywords: rayyan,systematic review
Requires-Python: <4.0,>=3.9
Requires-Dist: llama-index-core<0.15,>=0.13.0
Requires-Dist: rayyan-sdk~=1.0rc7
Requires-Dist: tenacity<9,>=8.2.3
Requires-Dist: tqdm<5,>=4.66.1
